MANIFEST.in
README.md
setup.py
atlas/__init__.py
atlas/agent.py
atlas/atlas.py
atlas/checker.py
atlas/cli.py
atlas/discovery.py
atlas/executor.py
atlas/loader.py
atlas/utils.py
atlas/version.py
atlas/client/__init__.py
atlas/client/agent_client.py
atlas/client/atlas_client.py
atlas/client/discovery_client.py
atlas/interpreters/__init__.py
atlas/interpreters/dummy_interpreter.py
atlas/interpreters/interpreter.py
atlas/interpreters/snips_interpreter.py
atlas/web/__init__.py
atlas/web/server.py
atlas/web/public/android-icon-144x144.png
atlas/web/public/android-icon-192x192.png
atlas/web/public/android-icon-36x36.png
atlas/web/public/android-icon-48x48.png
atlas/web/public/android-icon-72x72.png
atlas/web/public/android-icon-96x96.png
atlas/web/public/apple-icon-114x114.png
atlas/web/public/apple-icon-120x120.png
atlas/web/public/apple-icon-144x144.png
atlas/web/public/apple-icon-152x152.png
atlas/web/public/apple-icon-180x180.png
atlas/web/public/apple-icon-57x57.png
atlas/web/public/apple-icon-60x60.png
atlas/web/public/apple-icon-72x72.png
atlas/web/public/apple-icon-76x76.png
atlas/web/public/apple-icon-precomposed.png
atlas/web/public/apple-icon.png
atlas/web/public/browserconfig.xml
atlas/web/public/end_of_input.wav
atlas/web/public/favicon-16x16.png
atlas/web/public/favicon-32x32.png
atlas/web/public/favicon-96x96.png
atlas/web/public/favicon.ico
atlas/web/public/index.html
atlas/web/public/main.3325a672b032518e5dad.bundle.js
atlas/web/public/manifest.json
atlas/web/public/ms-icon-144x144.png
atlas/web/public/ms-icon-150x150.png
atlas/web/public/ms-icon-310x310.png
atlas/web/public/ms-icon-70x70.png
atlas/web/public/start_of_input.wav
atlas/web/public/sw.js
atlas_core.egg-info/PKG-INFO
atlas_core.egg-info/SOURCES.txt
atlas_core.egg-info/dependency_links.txt
atlas_core.egg-info/entry_points.txt
atlas_core.egg-info/requires.txt
atlas_core.egg-info/top_level.txt