Metadata-Version: 2.1
Name: atlas-core
Version: 1.2.0
Summary: An open-source assistant built for people
Home-page: https://github.com/atlassistant/atlas
Author: Julien LEICHER
License: GPL-3.0
Platform: UNKNOWN
Provides-Extra: snips
